LICENSE
MANIFEST.in
README.md
VERSION
setup.cfg
setup.py
src/stepfunctions/__init__.py
src/stepfunctions/exceptions.py
src/stepfunctions/inputs/__init__.py
src/stepfunctions/inputs/placeholders.py
src/stepfunctions/inputs/utils.py
src/stepfunctions/steps/__init__.py
src/stepfunctions/steps/choice_rule.py
src/stepfunctions/steps/compute.py
src/stepfunctions/steps/fields.py
src/stepfunctions/steps/integration_resources.py
src/stepfunctions/steps/service.py
src/stepfunctions/steps/states.py
src/stepfunctions/steps/utils.py
src/stepfunctions/template/__init__.py
src/stepfunctions/template/utils.py
src/stepfunctions_asl.egg-info/PKG-INFO
src/stepfunctions_asl.egg-info/SOURCES.txt
src/stepfunctions_asl.egg-info/dependency_links.txt
src/stepfunctions_asl.egg-info/requires.txt
src/stepfunctions_asl.egg-info/top_level.txt